flair_visual/__init__.py
flair_visual/simulation_result.py
flair_visual/animation/__init__.py
flair_visual/animation/animate.py
flair_visual/animation/base.py
flair_visual/animation/gate_event.py
flair_visual/animation/runtime/__init__.py
flair_visual/animation/runtime/aod.py
flair_visual/animation/runtime/atoms.py
flair_visual/animation/runtime/ppoly.py
flair_visual/animation/runtime/qpustate.py
flair_visual/animation/runtime/utils.py
flair_visual/simulation/__init__.py
flair_visual/simulation/cirq_backend.py
flair_visual/simulation/constructor.py
flair_visual/simulation/sample.py
flair_visual/simulation/schema.py
flair_visual-0.5.4.dist-info/METADATA
flair_visual-0.5.4.dist-info/WHEEL
flair_visual-0.5.4.dist-info/RECORD
